{
  "resourceType": "Bundle",
  "type": "transaction",
  "entry": [
    {
      "resource": {
        "resourceType": "Location",
        "meta": {
          "profile": [
            "http://ihe.net/fhir/StructureDefinition/IHE.mCSD.Location",
            "http://ihris.org/fhir/StructureDefinition/ihris-jurisdiction"
          ]
        },
        "id": "State-1001",
        "name": "ab Abia",
        "status": "active",
        "partOf": {
          "reference": "Location/NG"
        },
        "type": [
          {
            "coding": [
              {
                "system": "http://ihris.org/fhir/CodeSystem/ihris-jurisdiction",
                "code": "state"
              }
            ],
            "text": "State"
          }
        ],
        "physicalType": {
          "coding": [
            {
              "system": "http://hl7.org/fhir/codesystem-location-physical-type.html",
              "code": "jdn"
            }
          ],
          "text": "Jurisdiction"
        }
      },
      "request": {
        "method": "PUT",
        "url": "Location/State-1001"
      }
    },
    {
      "resource": {
        "resourceType": "Location",
        "meta": {
          "profile": [
            "http://ihe.net/fhir/StructureDefinition/IHE.mCSD.Location",
            "http://ihris.org/fhir/StructureDefinition/ihris-jurisdiction"
          ]
        },
        "id": "State-1002",
        "name": "ab Adamawa",
        "status": "active",
        "partOf": {
          "reference": "Location/NG"
        },
        "type": [
          {
            "coding": [
              {
                "system": "http://ihris.org/fhir/CodeSystem/ihris-jurisdiction",
                "code": "state"
              }
            ],
            "text": "State"
          }
        ],
        "physicalType": {
          "coding": [
            {
              "system": "http://hl7.org/fhir/codesystem-location-physical-type.html",
              "code": "jdn"
            }
          ],
          "text": "Jurisdiction"
        }
      },
      "request": {
        "method": "PUT",
        "url": "Location/State-1002"
      }
    },
    {
      "resource": {
        "resourceType": "Location",
        "meta": {
          "profile": [
            "http://ihe.net/fhir/StructureDefinition/IHE.mCSD.Location",
            "http://ihris.org/fhir/StructureDefinition/ihris-jurisdiction"
          ]
        },
        "id": "State-1003",
        "name": "ab Akwa Ibom",
        "status": "active",
        "partOf": {
          "reference": "Location/NG"
        },
        "type": [
          {
            "coding": [
              {
                "system": "http://ihris.org/fhir/CodeSystem/ihris-jurisdiction",
                "code": "state"
              }
            ],
            "text": "State"
          }
        ],
        "physicalType": {
          "coding": [
            {
              "system": "http://hl7.org/fhir/codesystem-location-physical-type.html",
              "code": "jdn"
            }
          ],
          "text": "Jurisdiction"
        }
      },
      "request": {
        "method": "PUT",
        "url": "Location/State-1003"
      }
    },
    {
      "resource": {
        "resourceType": "Location",
        "meta": {
          "profile": [
            "http://ihe.net/fhir/StructureDefinition/IHE.mCSD.Location",
            "http://ihris.org/fhir/StructureDefinition/ihris-jurisdiction"
          ]
        },
        "id": "State-1004",
        "name": "ab Anambra",
        "status": "active",
        "partOf": {
          "reference": "Location/NG"
        },
        "type": [
          {
            "coding": [
              {
                "system": "http://ihris.org/fhir/CodeSystem/ihris-jurisdiction",
                "code": "state"
              }
            ],
            "text": "State"
          }
        ],
        "physicalType": {
          "coding": [
            {
              "system": "http://hl7.org/fhir/codesystem-location-physical-type.html",
              "code": "jdn"
            }
          ],
          "text": "Jurisdiction"
        }
      },
      "request": {
        "method": "PUT",
        "url": "Location/State-1004"
      }
    },
    {
      "resource": {
        "resourceType": "Location",
        "meta": {
          "profile": [
            "http://ihe.net/fhir/StructureDefinition/IHE.mCSD.Location",
            "http://ihris.org/fhir/StructureDefinition/ihris-jurisdiction"
          ]
        },
        "id": "State-1005",
        "name": "ab Bauchi",
        "status": "active",
        "partOf": {
          "reference": "Location/NG"
        },
        "type": [
          {
            "coding": [
              {
                "system": "http://ihris.org/fhir/CodeSystem/ihris-jurisdiction",
                "code": "state"
              }
            ],
            "text": "State"
          }
        ],
        "physicalType": {
          "coding": [
            {
              "system": "http://hl7.org/fhir/codesystem-location-physical-type.html",
              "code": "jdn"
            }
          ],
          "text": "Jurisdiction"
        }
      },
      "request": {
        "method": "PUT",
        "url": "Location/State-1005"
      }
    },
    {
      "resource": {
        "resourceType": "Location",
        "meta": {
          "profile": [
            "http://ihe.net/fhir/StructureDefinition/IHE.mCSD.Location",
            "http://ihris.org/fhir/StructureDefinition/ihris-jurisdiction"
          ]
        },
        "id": "State-1006",
        "name": "ab Bayelsa",
        "status": "active",
        "partOf": {
          "reference": "Location/NG"
        },
        "type": [
          {
            "coding": [
              {
                "system": "http://ihris.org/fhir/CodeSystem/ihris-jurisdiction",
                "code": "state"
              }
            ],
            "text": "State"
          }
        ],
        "physicalType": {
          "coding": [
            {
              "system": "http://hl7.org/fhir/codesystem-location-physical-type.html",
              "code": "jdn"
            }
          ],
          "text": "Jurisdiction"
        }
      },
      "request": {
        "method": "PUT",
        "url": "Location/State-1006"
      }
    },
    {
      "resource": {
        "resourceType": "Location",
        "meta": {
          "profile": [
            "http://ihe.net/fhir/StructureDefinition/IHE.mCSD.Location",
            "http://ihris.org/fhir/StructureDefinition/ihris-jurisdiction"
          ]
        },
        "id": "State-1007",
        "name": "ab Benue",
        "status": "active",
        "partOf": {
          "reference": "Location/NG"
        },
        "type": [
          {
            "coding": [
              {
                "system": "http://ihris.org/fhir/CodeSystem/ihris-jurisdiction",
                "code": "state"
              }
            ],
            "text": "State"
          }
        ],
        "physicalType": {
          "coding": [
            {
              "system": "http://hl7.org/fhir/codesystem-location-physical-type.html",
              "code": "jdn"
            }
          ],
          "text": "Jurisdiction"
        }
      },
      "request": {
        "method": "PUT",
        "url": "Location/State-1007"
      }
    },
    {
      "resource": {
        "resourceType": "Location",
        "meta": {
          "profile": [
            "http://ihe.net/fhir/StructureDefinition/IHE.mCSD.Location",
            "http://ihris.org/fhir/StructureDefinition/ihris-jurisdiction"
          ]
        },
        "id": "State-1008",
        "name": "ab Borno",
        "status": "active",
        "partOf": {
          "reference": "Location/NG"
        },
        "type": [
          {
            "coding": [
              {
                "system": "http://ihris.org/fhir/CodeSystem/ihris-jurisdiction",
                "code": "state"
              }
            ],
            "text": "State"
          }
        ],
        "physicalType": {
          "coding": [
            {
              "system": "http://hl7.org/fhir/codesystem-location-physical-type.html",
              "code": "jdn"
            }
          ],
          "text": "Jurisdiction"
        }
      },
      "request": {
        "method": "PUT",
        "url": "Location/State-1008"
      }
    },
    {
      "resource": {
        "resourceType": "Location",
        "meta": {
          "profile": [
            "http://ihe.net/fhir/StructureDefinition/IHE.mCSD.Location",
            "http://ihris.org/fhir/StructureDefinition/ihris-jurisdiction"
          ]
        },
        "id": "State-1009",
        "name": "ab Cross River",
        "status": "active",
        "partOf": {
          "reference": "Location/NG"
        },
        "type": [
          {
            "coding": [
              {
                "system": "http://ihris.org/fhir/CodeSystem/ihris-jurisdiction",
                "code": "state"
              }
            ],
            "text": "State"
          }
        ],
        "physicalType": {
          "coding": [
            {
              "system": "http://hl7.org/fhir/codesystem-location-physical-type.html",
              "code": "jdn"
            }
          ],
          "text": "Jurisdiction"
        }
      },
      "request": {
        "method": "PUT",
        "url": "Location/State-1009"
      }
    },
    {
      "resource": {
        "resourceType": "Location",
        "meta": {
          "profile": [
            "http://ihe.net/fhir/StructureDefinition/IHE.mCSD.Location",
            "http://ihris.org/fhir/StructureDefinition/ihris-jurisdiction"
          ]
        },
        "id": "State-1010",
        "name": "ab Delta",
        "status": "active",
        "partOf": {
          "reference": "Location/NG"
        },
        "type": [
          {
            "coding": [
              {
                "system": "http://ihris.org/fhir/CodeSystem/ihris-jurisdiction",
                "code": "state"
              }
            ],
            "text": "State"
          }
        ],
        "physicalType": {
          "coding": [
            {
              "system": "http://hl7.org/fhir/codesystem-location-physical-type.html",
              "code": "jdn"
            }
          ],
          "text": "Jurisdiction"
        }
      },
      "request": {
        "method": "PUT",
        "url": "Location/State-1010"
      }
    },
    {
      "resource": {
        "resourceType": "Location",
        "meta": {
          "profile": [
            "http://ihe.net/fhir/StructureDefinition/IHE.mCSD.Location",
            "http://ihris.org/fhir/StructureDefinition/ihris-jurisdiction"
          ]
        },
        "id": "State-1011",
        "name": "ab Ebonyi",
        "status": "active",
        "partOf": {
          "reference": "Location/NG"
        },
        "type": [
          {
            "coding": [
              {
                "system": "http://ihris.org/fhir/CodeSystem/ihris-jurisdiction",
                "code": "state"
              }
            ],
            "text": "State"
          }
        ],
        "physicalType": {
          "coding": [
            {
              "system": "http://hl7.org/fhir/codesystem-location-physical-type.html",
              "code": "jdn"
            }
          ],
          "text": "Jurisdiction"
        }
      },
      "request": {
        "method": "PUT",
        "url": "Location/State-1011"
      }
    },
    {
      "resource": {
        "resourceType": "Location",
        "meta": {
          "profile": [
            "http://ihe.net/fhir/StructureDefinition/IHE.mCSD.Location",
            "http://ihris.org/fhir/StructureDefinition/ihris-jurisdiction"
          ]
        },
        "id": "State-1012",
        "name": "ab Edo",
        "status": "active",
        "partOf": {
          "reference": "Location/NG"
        },
        "type": [
          {
            "coding": [
              {
                "system": "http://ihris.org/fhir/CodeSystem/ihris-jurisdiction",
                "code": "state"
              }
            ],
            "text": "State"
          }
        ],
        "physicalType": {
          "coding": [
            {
              "system": "http://hl7.org/fhir/codesystem-location-physical-type.html",
              "code": "jdn"
            }
          ],
          "text": "Jurisdiction"
        }
      },
      "request": {
        "method": "PUT",
        "url": "Location/State-1012"
      }
    },
    {
      "resource": {
        "resourceType": "Location",
        "meta": {
          "profile": [
            "http://ihe.net/fhir/StructureDefinition/IHE.mCSD.Location",
            "http://ihris.org/fhir/StructureDefinition/ihris-jurisdiction"
          ]
        },
        "id": "State-1013",
        "name": "ab Ekiti",
        "status": "active",
        "partOf": {
          "reference": "Location/NG"
        },
        "type": [
          {
            "coding": [
              {
                "system": "http://ihris.org/fhir/CodeSystem/ihris-jurisdiction",
                "code": "state"
              }
            ],
            "text": "State"
          }
        ],
        "physicalType": {
          "coding": [
            {
              "system": "http://hl7.org/fhir/codesystem-location-physical-type.html",
              "code": "jdn"
            }
          ],
          "text": "Jurisdiction"
        }
      },
      "request": {
        "method": "PUT",
        "url": "Location/State-1013"
      }
    },
    {
      "resource": {
        "resourceType": "Location",
        "meta": {
          "profile": [
            "http://ihe.net/fhir/StructureDefinition/IHE.mCSD.Location",
            "http://ihris.org/fhir/StructureDefinition/ihris-jurisdiction"
          ]
        },
        "id": "State-1014",
        "name": "ab Enugu",
        "status": "active",
        "partOf": {
          "reference": "Location/NG"
        },
        "type": [
          {
            "coding": [
              {
                "system": "http://ihris.org/fhir/CodeSystem/ihris-jurisdiction",
                "code": "state"
              }
            ],
            "text": "State"
          }
        ],
        "physicalType": {
          "coding": [
            {
              "system": "http://hl7.org/fhir/codesystem-location-physical-type.html",
              "code": "jdn"
            }
          ],
          "text": "Jurisdiction"
        }
      },
      "request": {
        "method": "PUT",
        "url": "Location/State-1014"
      }
    },
    {
      "resource": {
        "resourceType": "Location",
        "meta": {
          "profile": [
            "http://ihe.net/fhir/StructureDefinition/IHE.mCSD.Location",
            "http://ihris.org/fhir/StructureDefinition/ihris-jurisdiction"
          ]
        },
        "id": "State-1015",
        "name": "ab Federal Capital Territory",
        "status": "active",
        "partOf": {
          "reference": "Location/NG"
        },
        "type": [
          {
            "coding": [
              {
                "system": "http://ihris.org/fhir/CodeSystem/ihris-jurisdiction",
                "code": "state"
              }
            ],
            "text": "State"
          }
        ],
        "physicalType": {
          "coding": [
            {
              "system": "http://hl7.org/fhir/codesystem-location-physical-type.html",
              "code": "jdn"
            }
          ],
          "text": "Jurisdiction"
        }
      },
      "request": {
        "method": "PUT",
        "url": "Location/State-1015"
      }
    },
    {
      "resource": {
        "resourceType": "Location",
        "meta": {
          "profile": [
            "http://ihe.net/fhir/StructureDefinition/IHE.mCSD.Location",
            "http://ihris.org/fhir/StructureDefinition/ihris-jurisdiction"
          ]
        },
        "id": "State-1016",
        "name": "ab Gombe",
        "status": "active",
        "partOf": {
          "reference": "Location/NG"
        },
        "type": [
          {
            "coding": [
              {
                "system": "http://ihris.org/fhir/CodeSystem/ihris-jurisdiction",
                "code": "state"
              }
            ],
            "text": "State"
          }
        ],
        "physicalType": {
          "coding": [
            {
              "system": "http://hl7.org/fhir/codesystem-location-physical-type.html",
              "code": "jdn"
            }
          ],
          "text": "Jurisdiction"
        }
      },
      "request": {
        "method": "PUT",
        "url": "Location/State-1016"
      }
    },
    {
      "resource": {
        "resourceType": "Location",
        "meta": {
          "profile": [
            "http://ihe.net/fhir/StructureDefinition/IHE.mCSD.Location",
            "http://ihris.org/fhir/StructureDefinition/ihris-jurisdiction"
          ]
        },
        "id": "State-1017",
        "name": "ab Imo",
        "status": "active",
        "partOf": {
          "reference": "Location/NG"
        },
        "type": [
          {
            "coding": [
              {
                "system": "http://ihris.org/fhir/CodeSystem/ihris-jurisdiction",
                "code": "state"
              }
            ],
            "text": "State"
          }
        ],
        "physicalType": {
          "coding": [
            {
              "system": "http://hl7.org/fhir/codesystem-location-physical-type.html",
              "code": "jdn"
            }
          ],
          "text": "Jurisdiction"
        }
      },
      "request": {
        "method": "PUT",
        "url": "Location/State-1017"
      }
    },
    {
      "resource": {
        "resourceType": "Location",
        "meta": {
          "profile": [
            "http://ihe.net/fhir/StructureDefinition/IHE.mCSD.Location",
            "http://ihris.org/fhir/StructureDefinition/ihris-jurisdiction"
          ]
        },
        "id": "State-1018",
        "name": "ab Jigawa",
        "status": "active",
        "partOf": {
          "reference": "Location/NG"
        },
        "type": [
          {
            "coding": [
              {
                "system": "http://ihris.org/fhir/CodeSystem/ihris-jurisdiction",
                "code": "state"
              }
            ],
            "text": "State"
          }
        ],
        "physicalType": {
          "coding": [
            {
              "system": "http://hl7.org/fhir/codesystem-location-physical-type.html",
              "code": "jdn"
            }
          ],
          "text": "Jurisdiction"
        }
      },
      "request": {
        "method": "PUT",
        "url": "Location/State-1018"
      }
    },
    {
      "resource": {
        "resourceType": "Location",
        "meta": {
          "profile": [
            "http://ihe.net/fhir/StructureDefinition/IHE.mCSD.Location",
            "http://ihris.org/fhir/StructureDefinition/ihris-jurisdiction"
          ]
        },
        "id": "State-1019",
        "name": "ab Kaduna",
        "status": "active",
        "partOf": {
          "reference": "Location/NG"
        },
        "type": [
          {
            "coding": [
              {
                "system": "http://ihris.org/fhir/CodeSystem/ihris-jurisdiction",
                "code": "state"
              }
            ],
            "text": "State"
          }
        ],
        "physicalType": {
          "coding": [
            {
              "system": "http://hl7.org/fhir/codesystem-location-physical-type.html",
              "code": "jdn"
            }
          ],
          "text": "Jurisdiction"
        }
      },
      "request": {
        "method": "PUT",
        "url": "Location/State-1019"
      }
    },
    {
      "resource": {
        "resourceType": "Location",
        "meta": {
          "profile": [
            "http://ihe.net/fhir/StructureDefinition/IHE.mCSD.Location",
            "http://ihris.org/fhir/StructureDefinition/ihris-jurisdiction"
          ]
        },
        "id": "State-1020",
        "name": "ab Kano",
        "status": "active",
        "partOf": {
          "reference": "Location/NG"
        },
        "type": [
          {
            "coding": [
              {
                "system": "http://ihris.org/fhir/CodeSystem/ihris-jurisdiction",
                "code": "state"
              }
            ],
            "text": "State"
          }
        ],
        "physicalType": {
          "coding": [
            {
              "system": "http://hl7.org/fhir/codesystem-location-physical-type.html",
              "code": "jdn"
            }
          ],
          "text": "Jurisdiction"
        }
      },
      "request": {
        "method": "PUT",
        "url": "Location/State-1020"
      }
    },
    {
      "resource": {
        "resourceType": "Location",
        "meta": {
          "profile": [
            "http://ihe.net/fhir/StructureDefinition/IHE.mCSD.Location",
            "http://ihris.org/fhir/StructureDefinition/ihris-jurisdiction"
          ]
        },
        "id": "State-1021",
        "name": "ab Katsina",
        "status": "active",
        "partOf": {
          "reference": "Location/NG"
        },
        "type": [
          {
            "coding": [
              {
                "system": "http://ihris.org/fhir/CodeSystem/ihris-jurisdiction",
                "code": "state"
              }
            ],
            "text": "State"
          }
        ],
        "physicalType": {
          "coding": [
            {
              "system": "http://hl7.org/fhir/codesystem-location-physical-type.html",
              "code": "jdn"
            }
          ],
          "text": "Jurisdiction"
        }
      },
      "request": {
        "method": "PUT",
        "url": "Location/State-1021"
      }
    },
    {
      "resource": {
        "resourceType": "Location",
        "meta": {
          "profile": [
            "http://ihe.net/fhir/StructureDefinition/IHE.mCSD.Location",
            "http://ihris.org/fhir/StructureDefinition/ihris-jurisdiction"
          ]
        },
        "id": "State-1022",
        "name": "ab Kebbi",
        "status": "active",
        "partOf": {
          "reference": "Location/NG"
        },
        "type": [
          {
            "coding": [
              {
                "system": "http://ihris.org/fhir/CodeSystem/ihris-jurisdiction",
                "code": "state"
              }
            ],
            "text": "State"
          }
        ],
        "physicalType": {
          "coding": [
            {
              "system": "http://hl7.org/fhir/codesystem-location-physical-type.html",
              "code": "jdn"
            }
          ],
          "text": "Jurisdiction"
        }
      },
      "request": {
        "method": "PUT",
        "url": "Location/State-1022"
      }
    },
    {
      "resource": {
        "resourceType": "Location",
        "meta": {
          "profile": [
            "http://ihe.net/fhir/StructureDefinition/IHE.mCSD.Location",
            "http://ihris.org/fhir/StructureDefinition/ihris-jurisdiction"
          ]
        },
        "id": "State-1023",
        "name": "ab Kogi",
        "status": "active",
        "partOf": {
          "reference": "Location/NG"
        },
        "type": [
          {
            "coding": [
              {
                "system": "http://ihris.org/fhir/CodeSystem/ihris-jurisdiction",
                "code": "state"
              }
            ],
            "text": "State"
          }
        ],
        "physicalType": {
          "coding": [
            {
              "system": "http://hl7.org/fhir/codesystem-location-physical-type.html",
              "code": "jdn"
            }
          ],
          "text": "Jurisdiction"
        }
      },
      "request": {
        "method": "PUT",
        "url": "Location/State-1023"
      }
    },
    {
      "resource": {
        "resourceType": "Location",
        "meta": {
          "profile": [
            "http://ihe.net/fhir/StructureDefinition/IHE.mCSD.Location",
            "http://ihris.org/fhir/StructureDefinition/ihris-jurisdiction"
          ]
        },
        "id": "State-1024",
        "name": "ab Kwara",
        "status": "active",
        "partOf": {
          "reference": "Location/NG"
        },
        "type": [
          {
            "coding": [
              {
                "system": "http://ihris.org/fhir/CodeSystem/ihris-jurisdiction",
                "code": "state"
              }
            ],
            "text": "State"
          }
        ],
        "physicalType": {
          "coding": [
            {
              "system": "http://hl7.org/fhir/codesystem-location-physical-type.html",
              "code": "jdn"
            }
          ],
          "text": "Jurisdiction"
        }
      },
      "request": {
        "method": "PUT",
        "url": "Location/State-1024"
      }
    },
    {
      "resource": {
        "resourceType": "Location",
        "meta": {
          "profile": [
            "http://ihe.net/fhir/StructureDefinition/IHE.mCSD.Location",
            "http://ihris.org/fhir/StructureDefinition/ihris-jurisdiction"
          ]
        },
        "id": "State-1025",
        "name": "ab Lagos",
        "status": "active",
        "partOf": {
          "reference": "Location/NG"
        },
        "type": [
          {
            "coding": [
              {
                "system": "http://ihris.org/fhir/CodeSystem/ihris-jurisdiction",
                "code": "state"
              }
            ],
            "text": "State"
          }
        ],
        "physicalType": {
          "coding": [
            {
              "system": "http://hl7.org/fhir/codesystem-location-physical-type.html",
              "code": "jdn"
            }
          ],
          "text": "Jurisdiction"
        }
      },
      "request": {
        "method": "PUT",
        "url": "Location/State-1025"
      }
    },
    {
      "resource": {
        "resourceType": "Location",
        "meta": {
          "profile": [
            "http://ihe.net/fhir/StructureDefinition/IHE.mCSD.Location",
            "http://ihris.org/fhir/StructureDefinition/ihris-jurisdiction"
          ]
        },
        "id": "State-1026",
        "name": "ab Nasarawa",
        "status": "active",
        "partOf": {
          "reference": "Location/NG"
        },
        "type": [
          {
            "coding": [
              {
                "system": "http://ihris.org/fhir/CodeSystem/ihris-jurisdiction",
                "code": "state"
              }
            ],
            "text": "State"
          }
        ],
        "physicalType": {
          "coding": [
            {
              "system": "http://hl7.org/fhir/codesystem-location-physical-type.html",
              "code": "jdn"
            }
          ],
          "text": "Jurisdiction"
        }
      },
      "request": {
        "method": "PUT",
        "url": "Location/State-1026"
      }
    },
    {
      "resource": {
        "resourceType": "Location",
        "meta": {
          "profile": [
            "http://ihe.net/fhir/StructureDefinition/IHE.mCSD.Location",
            "http://ihris.org/fhir/StructureDefinition/ihris-jurisdiction"
          ]
        },
        "id": "State-1027",
        "name": "ab Niger",
        "status": "active",
        "partOf": {
          "reference": "Location/NG"
        },
        "type": [
          {
            "coding": [
              {
                "system": "http://ihris.org/fhir/CodeSystem/ihris-jurisdiction",
                "code": "state"
              }
            ],
            "text": "State"
          }
        ],
        "physicalType": {
          "coding": [
            {
              "system": "http://hl7.org/fhir/codesystem-location-physical-type.html",
              "code": "jdn"
            }
          ],
          "text": "Jurisdiction"
        }
      },
      "request": {
        "method": "PUT",
        "url": "Location/State-1027"
      }
    },
    {
      "resource": {
        "resourceType": "Location",
        "meta": {
          "profile": [
            "http://ihe.net/fhir/StructureDefinition/IHE.mCSD.Location",
            "http://ihris.org/fhir/StructureDefinition/ihris-jurisdiction"
          ]
        },
        "id": "State-1028",
        "name": "ab Ogun",
        "status": "active",
        "partOf": {
          "reference": "Location/NG"
        },
        "type": [
          {
            "coding": [
              {
                "system": "http://ihris.org/fhir/CodeSystem/ihris-jurisdiction",
                "code": "state"
              }
            ],
            "text": "State"
          }
        ],
        "physicalType": {
          "coding": [
            {
              "system": "http://hl7.org/fhir/codesystem-location-physical-type.html",
              "code": "jdn"
            }
          ],
          "text": "Jurisdiction"
        }
      },
      "request": {
        "method": "PUT",
        "url": "Location/State-1028"
      }
    },
    {
      "resource": {
        "resourceType": "Location",
        "meta": {
          "profile": [
            "http://ihe.net/fhir/StructureDefinition/IHE.mCSD.Location",
            "http://ihris.org/fhir/StructureDefinition/ihris-jurisdiction"
          ]
        },
        "id": "State-1029",
        "name": "ab Ondo",
        "status": "active",
        "partOf": {
          "reference": "Location/NG"
        },
        "type": [
          {
            "coding": [
              {
                "system": "http://ihris.org/fhir/CodeSystem/ihris-jurisdiction",
                "code": "state"
              }
            ],
            "text": "State"
          }
        ],
        "physicalType": {
          "coding": [
            {
              "system": "http://hl7.org/fhir/codesystem-location-physical-type.html",
              "code": "jdn"
            }
          ],
          "text": "Jurisdiction"
        }
      },
      "request": {
        "method": "PUT",
        "url": "Location/State-1029"
      }
    },
    {
      "resource": {
        "resourceType": "Location",
        "meta": {
          "profile": [
            "http://ihe.net/fhir/StructureDefinition/IHE.mCSD.Location",
            "http://ihris.org/fhir/StructureDefinition/ihris-jurisdiction"
          ]
        },
        "id": "State-1030",
        "name": "ab Osun",
        "status": "active",
        "partOf": {
          "reference": "Location/NG"
        },
        "type": [
          {
            "coding": [
              {
                "system": "http://ihris.org/fhir/CodeSystem/ihris-jurisdiction",
                "code": "state"
              }
            ],
            "text": "State"
          }
        ],
        "physicalType": {
          "coding": [
            {
              "system": "http://hl7.org/fhir/codesystem-location-physical-type.html",
              "code": "jdn"
            }
          ],
          "text": "Jurisdiction"
        }
      },
      "request": {
        "method": "PUT",
        "url": "Location/State-1030"
      }
    },
    {
      "resource": {
        "resourceType": "Location",
        "meta": {
          "profile": [
            "http://ihe.net/fhir/StructureDefinition/IHE.mCSD.Location",
            "http://ihris.org/fhir/StructureDefinition/ihris-jurisdiction"
          ]
        },
        "id": "State-1031",
        "name": "ab Oyo",
        "status": "active",
        "partOf": {
          "reference": "Location/NG"
        },
        "type": [
          {
            "coding": [
              {
                "system": "http://ihris.org/fhir/CodeSystem/ihris-jurisdiction",
                "code": "state"
              }
            ],
            "text": "State"
          }
        ],
        "physicalType": {
          "coding": [
            {
              "system": "http://hl7.org/fhir/codesystem-location-physical-type.html",
              "code": "jdn"
            }
          ],
          "text": "Jurisdiction"
        }
      },
      "request": {
        "method": "PUT",
        "url": "Location/State-1031"
      }
    },
    {
      "resource": {
        "resourceType": "Location",
        "meta": {
          "profile": [
            "http://ihe.net/fhir/StructureDefinition/IHE.mCSD.Location",
            "http://ihris.org/fhir/StructureDefinition/ihris-jurisdiction"
          ]
        },
        "id": "State-1032",
        "name": "ab Plateau",
        "status": "active",
        "partOf": {
          "reference": "Location/NG"
        },
        "type": [
          {
            "coding": [
              {
                "system": "http://ihris.org/fhir/CodeSystem/ihris-jurisdiction",
                "code": "state"
              }
            ],
            "text": "State"
          }
        ],
        "physicalType": {
          "coding": [
            {
              "system": "http://hl7.org/fhir/codesystem-location-physical-type.html",
              "code": "jdn"
            }
          ],
          "text": "Jurisdiction"
        }
      },
      "request": {
        "method": "PUT",
        "url": "Location/State-1032"
      }
    },
    {
      "resource": {
        "resourceType": "Location",
        "meta": {
          "profile": [
            "http://ihe.net/fhir/StructureDefinition/IHE.mCSD.Location",
            "http://ihris.org/fhir/StructureDefinition/ihris-jurisdiction"
          ]
        },
        "id": "State-1033",
        "name": "ab Rivers",
        "status": "active",
        "partOf": {
          "reference": "Location/NG"
        },
        "type": [
          {
            "coding": [
              {
                "system": "http://ihris.org/fhir/CodeSystem/ihris-jurisdiction",
                "code": "state"
              }
            ],
            "text": "State"
          }
        ],
        "physicalType": {
          "coding": [
            {
              "system": "http://hl7.org/fhir/codesystem-location-physical-type.html",
              "code": "jdn"
            }
          ],
          "text": "Jurisdiction"
        }
      },
      "request": {
        "method": "PUT",
        "url": "Location/State-1033"
      }
    },
    {
      "resource": {
        "resourceType": "Location",
        "meta": {
          "profile": [
            "http://ihe.net/fhir/StructureDefinition/IHE.mCSD.Location",
            "http://ihris.org/fhir/StructureDefinition/ihris-jurisdiction"
          ]
        },
        "id": "State-1034",
        "name": "ab Sokoto",
        "status": "active",
        "partOf": {
          "reference": "Location/NG"
        },
        "type": [
          {
            "coding": [
              {
                "system": "http://ihris.org/fhir/CodeSystem/ihris-jurisdiction",
                "code": "state"
              }
            ],
            "text": "State"
          }
        ],
        "physicalType": {
          "coding": [
            {
              "system": "http://hl7.org/fhir/codesystem-location-physical-type.html",
              "code": "jdn"
            }
          ],
          "text": "Jurisdiction"
        }
      },
      "request": {
        "method": "PUT",
        "url": "Location/State-1034"
      }
    },
    {
      "resource": {
        "resourceType": "Location",
        "meta": {
          "profile": [
            "http://ihe.net/fhir/StructureDefinition/IHE.mCSD.Location",
            "http://ihris.org/fhir/StructureDefinition/ihris-jurisdiction"
          ]
        },
        "id": "State-1035",
        "name": "ab Taraba",
        "status": "active",
        "partOf": {
          "reference": "Location/NG"
        },
        "type": [
          {
            "coding": [
              {
                "system": "http://ihris.org/fhir/CodeSystem/ihris-jurisdiction",
                "code": "state"
              }
            ],
            "text": "State"
          }
        ],
        "physicalType": {
          "coding": [
            {
              "system": "http://hl7.org/fhir/codesystem-location-physical-type.html",
              "code": "jdn"
            }
          ],
          "text": "Jurisdiction"
        }
      },
      "request": {
        "method": "PUT",
        "url": "Location/State-1035"
      }
    },
    {
      "resource": {
        "resourceType": "Location",
        "meta": {
          "profile": [
            "http://ihe.net/fhir/StructureDefinition/IHE.mCSD.Location",
            "http://ihris.org/fhir/StructureDefinition/ihris-jurisdiction"
          ]
        },
        "id": "State-1036",
        "name": "ab Yobe",
        "status": "active",
        "partOf": {
          "reference": "Location/NG"
        },
        "type": [
          {
            "coding": [
              {
                "system": "http://ihris.org/fhir/CodeSystem/ihris-jurisdiction",
                "code": "state"
              }
            ],
            "text": "State"
          }
        ],
        "physicalType": {
          "coding": [
            {
              "system": "http://hl7.org/fhir/codesystem-location-physical-type.html",
              "code": "jdn"
            }
          ],
          "text": "Jurisdiction"
        }
      },
      "request": {
        "method": "PUT",
        "url": "Location/State-1036"
      }
    },
    {
      "resource": {
        "resourceType": "Location",
        "meta": {
          "profile": [
            "http://ihe.net/fhir/StructureDefinition/IHE.mCSD.Location",
            "http://ihris.org/fhir/StructureDefinition/ihris-jurisdiction"
          ]
        },
        "id": "State-1037",
        "name": "ab Zamfara",
        "status": "active",
        "partOf": {
          "reference": "Location/NG"
        },
        "type": [
          {
            "coding": [
              {
                "system": "http://ihris.org/fhir/CodeSystem/ihris-jurisdiction",
                "code": "state"
              }
            ],
            "text": "State"
          }
        ],
        "physicalType": {
          "coding": [
            {
              "system": "http://hl7.org/fhir/codesystem-location-physical-type.html",
              "code": "jdn"
            }
          ],
          "text": "Jurisdiction"
        }
      },
      "request": {
        "method": "PUT",
        "url": "Location/State-1037"
      }
    }
  ]
}